{
  "minging": [
    {
      "id": 1,
      "pool_id": 0,
      "token0": "0x0298c2b32eaE4da002a15f36fdf7615BEa3DA047",
      "token1": "0x5545153CCFcA01fbd7Dd11C0b23ba694D9509A6F",
      "alloc_mdx_amt": "10172169613660462097539",
      "total_quantity": "3372096223110465002499455579",
      "pool_quantity": "10572435085103363332655423",
      "alloc_point": "1364",
      "apy": "1704.2662063018374",
      "symbol0": "HUSD",
      "symbol1": "HT"
    },
    {
      "id": 2,
      "pool_id": 1,
      "token0": "0x64FF637fB478863B7468bc97D30a5bF3A428a1fD",
      "token1": "0xa71EdC38d189767582C38A3145b5873052c3e47a",
      "alloc_mdx_amt": "7927089209573067479199",
      "total_quantity": "3402002643467611165247490241",
      "pool_quantity": "8191322691191196472553970",
      "alloc_point": "1364",
      "apy": "2199.5911082993357",
      "symbol0": "ETH",
      "symbol1": "USDT"
    },
    {
      "id": 3,
      "pool_id": 2,
      "token0": "0x66a79D23E58475D2738179Ca52cd0b41d73f0BEa",
      "token1": "0xa71EdC38d189767582C38A3145b5873052c3e47a",
      "alloc_mdx_amt": "8259122884351186235198",
      "total_quantity": "3408966021874380269533827733",
      "pool_quantity": "8536223899725913655297079",
      "alloc_point": "1364",
      "apy": "2111.971431210369",
      "symbol0": "HBTC",
      "symbol1": "USDT"
    },
    {
      "id": 4,
      "pool_id": 3,
      "token0": "0x0298c2b32eaE4da002a15f36fdf7615BEa3DA047",
      "token1": "0xa71EdC38d189767582C38A3145b5873052c3e47a",
      "alloc_mdx_amt": "21546906521550246461929",
      "total_quantity": "9048924935813157394611926072",
      "pool_quantity": "22347567018370672557785451",
      "alloc_point": "3637",
      "apy": "2149.9500844294307",
      "symbol0": "HUSD",
      "symbol1": "USDT"
    },
    {
      "id": 5,
      "pool_id": 4,
      "token0": "0x25D2e80cB6B86881Fd7e07dd263Fb79f4AbE033c",
      "token1": "0xa71EdC38d189767582C38A3145b5873052c3e47a",
      "alloc_mdx_amt": "45550377280682312561161",
      "total_quantity": "597932876787930960180974855",
      "pool_quantity": "52636056758562888447961803",
      "alloc_point": "182",
      "apy": "45.66897660764821",
      "symbol0": "MDX",
      "symbol1": "USDT"
    },
    {
      "id": 6,
      "pool_id": 5,
      "token0": "0x0298c2b32eaE4da002a15f36fdf7615BEa3DA047",
      "token1": "0xa042fb0e60125A4022670014AC121931e7501Af4",
      "alloc_mdx_amt": "11099620038540727572366",
      "total_quantity": "266687580961150616183159672",
      "pool_quantity": "11527244569986325912579287",
      "alloc_point": "91",
      "apy": "104.26996667177453",
      "symbol0": "HUSD",
      "symbol1": "BAG"
    },
    {
      "id": 7,
      "pool_id": 6,
      "token0": "0x66a79D23E58475D2738179Ca52cd0b41d73f0BEa",
      "token1": "0xa042fb0e60125A4022670014AC121931e7501Af4",
      "alloc_mdx_amt": "1566407610421839890312",
      "total_quantity": "229876751941850833396844648",
      "pool_quantity": "1608543164312581744398069",
      "alloc_point": "91",
      "apy": "747.1768661585246",
      "symbol0": "HBTC",
      "symbol1": "BAG"
    },
    {
      "id": 8,
      "pool_id": 7,
      "token0": "0xA2c49cEe16a5E5bDEFDe931107dc1fae9f7773E3",
      "token1": "0xa71EdC38d189767582C38A3145b5873052c3e47a",
      "alloc_mdx_amt": "1576270449601903528377",
      "total_quantity": "694845293390976778931740144",
      "pool_quantity": "1622679621954403127442920",
      "alloc_point": "273",
      "apy": "2222.298643362952",
      "symbol0": "HDOT",
      "symbol1": "USDT"
    },
    {
      "id": 9,
      "pool_id": 8,
      "token0": "0xa71EdC38d189767582C38A3145b5873052c3e47a",
      "token1": "0xecb56cf772B5c9A6907FB7d32387Da2fCbfB63b4",
      "alloc_mdx_amt": "1581526367086757020780",
      "total_quantity": "681902524984988244504852081",
      "pool_quantity": "1648575389904078197133846",
      "alloc_point": "273",
      "apy": "2219.4000059163714",
      "symbol0": "USDT",
      "symbol1": "HLTC"
    },
    {
      "id": 10,
      "pool_id": 9,
      "token0": "0xa71EdC38d189767582C38A3145b5873052c3e47a",
      "token1": "0xeF3CEBD77E0C52cb6f60875d9306397B5Caca375",
      "alloc_mdx_amt": "1076256544257331906390",
      "total_quantity": "681062801943443217525471306",
      "pool_quantity": "1242762698206065923448618",
      "alloc_point": "273",
      "apy": "2948.9076731442105",
      "symbol0": "USDT",
      "symbol1": "HBCH"
    },
    {
      "id": 11,
      "pool_id": 10,
      "token0": "0xa71EdC38d189767582C38A3145b5873052c3e47a",
      "token1": "0xE499Ef4616993730CEd0f31FA2703B92B50bB536",
      "alloc_mdx_amt": "665317552931771134333",
      "total_quantity": "108638387211458907219697101",
      "pool_quantity": "686046205214634606241033",
      "alloc_point": "46",
      "apy": "885.6031434279323",
      "symbol0": "USDT",
      "symbol1": "HPT"
    },
    {
      "id": 12,
      "pool_id": 11,
      "token0": "0x5545153CCFcA01fbd7Dd11C0b23ba694D9509A6F",
      "token1": "0xa71EdC38d189767582C38A3145b5873052c3e47a",
      "alloc_mdx_amt": "26156191684469452413472",
      "total_quantity": "422475845725926426134348439",
      "pool_quantity": "27933295985140530032330461",
      "alloc_point": "538",
      "apy": "254.3707973670871",
      "symbol0": "HT",
      "symbol1": "USDT"
    },
    {
      "id": 13,
      "pool_id": 12,
      "token0": "0xa71EdC38d189767582C38A3145b5873052c3e47a",
      "token1": "0xae3a768f9aB104c69A7CD6041fE16fFa235d1810",
      "alloc_mdx_amt": "1893409809212887662452",
      "total_quantity": "44567702079418992303225245",
      "pool_quantity": "1976500419023016165343491",
      "alloc_point": "504",
      "apy": "3464.608821225544",
      "symbol0": "USDT"
    }
  ],
  "single": [
    {
      "totalUsdtValue": 64446331.85137231,
      "tokenPriceInUsdt": 11.477400160915721,
      "poolWeight": 0,
      "symbol": "WHT",
      "apy": 0
    },
    {
      "totalUsdtValue": 741698.8944200551,
      "tokenPriceInUsdt": 46860.773920620355,
      "poolWeight": 0,
      "symbol": "HBTC",
      "apy": 0
    },
    {
      "totalUsdtValue": 757907.3607258628,
      "tokenPriceInUsdt": 0.9996068931547512,
      "poolWeight": 0,
      "symbol": "HUSD",
      "apy": 0
    },
    {
      "totalUsdtValue": 303592.44631373836,
      "tokenPriceInUsdt": 1758.4380209201881,
      "poolWeight": 0,
      "symbol": "ETH",
      "apy": 0
    },
    {
      "totalUsdtValue": 288434.2465329298,
      "tokenPriceInWeth": 1,
      "poolWeight": 0,
      "symbol": "USDT",
      "apy": 0
    },
    {
      "totalUsdtValue": 7378377.255710056,
      "tokenPriceInUsdt": 507.13136931331064,
      "poolWeight": 0,
      "symbol": "HBCH",
      "apy": 0
    },
    {
      "totalUsdtValue": 8964.618963878778,
      "tokenPriceInUsdt": 23.01013338123224,
      "poolWeight": 0,
      "symbol": "HDOT",
      "apy": 0
    },
    {
      "totalUsdtValue": 49445.528320569014,
      "tokenPriceInUsdt": 175.6540758963782,
      "poolWeight": 0,
      "symbol": "HLTC",
      "apy": 0
    }
  ],
  "lps": [
    {
      "totalUsdtValue": 211256396.2910819,
      "tokenPriceInUsdt": 46859.324056228674,
      "poolWeight": 0.1633,
      "symbol": "HBTC/USDT",
      "apy": 101.62647734009352
    },
    {
      "totalUsdtValue": 166189043.84639484,
      "tokenPriceInUsdt": 1758.451748038235,
      "poolWeight": 0.144,
      "symbol": "ETH/USDT",
      "apy": 113.91755555403861
    },
    {
      "totalUsdtValue": 78097567.93894388,
      "tokenPriceInUsdt": 0.9995844743628677,
      "poolWeight": 0.025,
      "symbol": "HUSD/USDT",
      "apy": 42.085554483122614
    },
    {
      "totalUsdtValue": 47199267.383799076,
      "tokenPriceInUsdt": 175.65632446089964,
      "poolWeight": 0.042,
      "symbol": "HLTC/USDT",
      "apy": 116.98888103345644
    },
    {
      "totalUsdtValue": 43204855.01582404,
      "tokenPriceInUsdt": 507.1635599389041,
      "poolWeight": 0.042,
      "symbol": "HBCH/USDT",
      "apy": 127.80483755372359
    },
    {
      "totalUsdtValue": 38452625.88304449,
      "tokenPriceInUsdt": 23.010677223835476,
      "poolWeight": 0.042,
      "symbol": "HDOT/USDT",
      "apy": 143.59980235483422
    },
    {
      "totalUsdtValue": 16714944.97483809,
      "tokenPriceInUsdt": 42.62823291858284,
      "poolWeight": 0.022,
      "symbol": "HFIL/USDT",
      "apy": 173.04070822779087
    },
    {
      "totalUsdtValue": 69461565.94330218,
      "tokenPriceInUsdt": 3.126473629500118,
      "poolWeight": 0.245,
      "symbol": "MDX/USDT",
      "apy": 463.7159870701857
    },
    {
      "totalUsdtValue": 79977807.98434077,
      "tokenPriceInUsdt": 11.47514417881053,
      "poolWeight": 0.092,
      "symbol": "WHT/HUSD",
      "apy": 151.23380701038167
    },
    {
      "totalUsdtValue": 77734404.73526467,
      "tokenPriceInUsdt": 11.47496045571656,
      "poolWeight": 0.085,
      "symbol": "WHT/USDT",
      "apy": 143.7593838884736
    },
    {
      "totalUsdtValue": 3256768.3853754383,
      "tokenPriceInUsdt": 0.008235484057356558,
      "poolWeight": 0.0063,
      "symbol": "HPT/USDT",
      "apy": 254.32217570146713
    },
    {
      "totalUsdtValue": 26831244.765279874,
      "tokenPriceInUsdt": 3.1264150063287084,
      "poolWeight": 0.0885,
      "symbol": "MDX/WHT",
      "apy": 433.6436626974604
    }
  ],
  "time": "2021-02-10 06:43"
}