{
  "minging": [
    {
      "id": 1,
      "pool_id": 0,
      "token0": "0x0298c2b32eaE4da002a15f36fdf7615BEa3DA047",
      "token1": "0x5545153CCFcA01fbd7Dd11C0b23ba694D9509A6F",
      "alloc_mdx_amt": "6508128722342397487987",
      "total_quantity": "1712724721737256728660325432",
      "pool_quantity": "6668498104568087831101701",
      "alloc_point": "150",
      "apy": "2625.9861917861667",
      "symbol0": "HUSD",
      "symbol1": "HT"
    },
    {
      "id": 2,
      "pool_id": 1,
      "token0": "0x64FF637fB478863B7468bc97D30a5bF3A428a1fD",
      "token1": "0xa71EdC38d189767582C38A3145b5873052c3e47a",
      "alloc_mdx_amt": "4638319712487115742872",
      "total_quantity": "1728795955975907199384543793",
      "pool_quantity": "4752861988970153051364398",
      "alloc_point": "150",
      "apy": "3544.9185475823733",
      "symbol0": "ETH",
      "symbol1": "USDT"
    },
    {
      "id": 3,
      "pool_id": 2,
      "token0": "0x66a79D23E58475D2738179Ca52cd0b41d73f0BEa",
      "token1": "0xa71EdC38d189767582C38A3145b5873052c3e47a",
      "alloc_mdx_amt": "5423271856472734407256",
      "total_quantity": "1732445991971274414857438896",
      "pool_quantity": "5567641783099989253955758",
      "alloc_point": "150",
      "apy": "3150.7979474347867",
      "symbol0": "HBTC",
      "symbol1": "USDT"
    },
    {
      "id": 4,
      "pool_id": 3,
      "token0": "0x0298c2b32eaE4da002a15f36fdf7615BEa3DA047",
      "token1": "0xa71EdC38d189767582C38A3145b5873052c3e47a",
      "alloc_mdx_amt": "17095361448307822265129",
      "total_quantity": "4620105811595215324724048998",
      "pool_quantity": "17577879968759579613601126",
      "alloc_point": "400",
      "apy": "2688.416428146072",
      "symbol0": "HUSD",
      "symbol1": "USDT"
    },
    {
      "id": 5,
      "pool_id": 4,
      "token0": "0x25D2e80cB6B86881Fd7e07dd263Fb79f4AbE033c",
      "token1": "0xa71EdC38d189767582C38A3145b5873052c3e47a",
      "alloc_mdx_amt": "34944383395418643216760",
      "total_quantity": "341369541084837829165103340",
      "pool_quantity": "44049927562062115482763852",
      "alloc_point": "20",
      "apy": "53.125885849172185",
      "symbol0": "MDX",
      "symbol1": "USDT"
    },
    {
      "id": 6,
      "pool_id": 5,
      "token0": "0x0298c2b32eaE4da002a15f36fdf7615BEa3DA047",
      "token1": "0xa042fb0e60125A4022670014AC121931e7501Af4",
      "alloc_mdx_amt": "12858023225456199087841",
      "total_quantity": "145995987575183476339608953",
      "pool_quantity": "13041055347050189778349861",
      "alloc_point": "10",
      "apy": "89.72341658081254",
      "symbol0": "HUSD",
      "symbol1": "BAG"
    },
    {
      "id": 7,
      "pool_id": 6,
      "token0": "0x66a79D23E58475D2738179Ca52cd0b41d73f0BEa",
      "token1": "0xa042fb0e60125A4022670014AC121931e7501Af4",
      "alloc_mdx_amt": "1378687777478401644399",
      "total_quantity": "120076403507666843634161654",
      "pool_quantity": "1418881928664934054449210",
      "alloc_point": "10",
      "apy": "823.8783625943416",
      "symbol0": "HBTC",
      "symbol1": "BAG"
    },
    {
      "id": 8,
      "pool_id": 7,
      "token0": "0xA2c49cEe16a5E5bDEFDe931107dc1fae9f7773E3",
      "token1": "0xa71EdC38d189767582C38A3145b5873052c3e47a",
      "alloc_mdx_amt": "782797630197178719675",
      "total_quantity": "346948325561782485498422517",
      "pool_quantity": "801654605136440389142691",
      "alloc_point": "30",
      "apy": "4391.357551345573",
      "symbol0": "HDOT",
      "symbol1": "USDT"
    },
    {
      "id": 9,
      "pool_id": 8,
      "token0": "0xa71EdC38d189767582C38A3145b5873052c3e47a",
      "token1": "0xecb56cf772B5c9A6907FB7d32387Da2fCbfB63b4",
      "alloc_mdx_amt": "511545306145267170109",
      "total_quantity": "345493718909879414778675726",
      "pool_quantity": "521293911899619770384193",
      "alloc_point": "30",
      "apy": "6778.812536570034",
      "symbol0": "USDT",
      "symbol1": "HLTC"
    },
    {
      "id": 10,
      "pool_id": 9,
      "token0": "0xa71EdC38d189767582C38A3145b5873052c3e47a",
      "token1": "0xeF3CEBD77E0C52cb6f60875d9306397B5Caca375",
      "alloc_mdx_amt": "498593697956287867456",
      "total_quantity": "344981681622494657940238697",
      "pool_quantity": "510492479903965030258313",
      "alloc_point": "30",
      "apy": "7049.358617506329",
      "symbol0": "USDT",
      "symbol1": "HBCH"
    },
    {
      "id": 11,
      "pool_id": 10,
      "token0": "0xa71EdC38d189767582C38A3145b5873052c3e47a",
      "token1": "0xE499Ef4616993730CEd0f31FA2703B92B50bB536",
      "alloc_mdx_amt": "210336876356571292788",
      "total_quantity": "53052678398858563183075423",
      "pool_quantity": "214246216898979040127309",
      "alloc_point": "5",
      "apy": "2728.279899001797",
      "symbol0": "USDT",
      "symbol1": "HPT"
    },
    {
      "id": 12,
      "pool_id": 11,
      "token0": "0x5545153CCFcA01fbd7Dd11C0b23ba694D9509A6F",
      "token1": "0xa71EdC38d189767582C38A3145b5873052c3e47a",
      "alloc_mdx_amt": "7940521702399367994955",
      "total_quantity": "173167475162426162875364061",
      "pool_quantity": "8183207354376676833220852",
      "alloc_point": "15",
      "apy": "214.5218540850221",
      "symbol0": "HT",
      "symbol1": "USDT"
    }
  ],
  "single": [
    {
      "totalUsdtValue": 67124338.62158234,
      "tokenPriceInUsdt": 6.380109720990985,
      "poolWeight": 0.0054,
      "symbol": "WHT",
      "apy": 10.30992198841695
    },
    {
      "totalUsdtValue": 101965749.06699196,
      "tokenPriceInUsdt": 34304.945360151796,
      "poolWeight": 0.0048,
      "symbol": "HBTC",
      "apy": 6.032933834656088
    },
    {
      "totalUsdtValue": 6115179.66940969,
      "tokenPriceInUsdt": 0.9988883694568609,
      "poolWeight": 0.0009,
      "symbol": "HUSD",
      "apy": 18.861443493215777
    },
    {
      "totalUsdtValue": 66290346.3395438,
      "tokenPriceInUsdt": 1377.9677199562113,
      "poolWeight": 0.0039,
      "symbol": "ETH",
      "apy": 7.5397328470242995
    },
    {
      "totalUsdtValue": 19095760.98452099,
      "tokenPriceInWeth": 1,
      "poolWeight": 0.0015,
      "symbol": "USDT",
      "apy": 10.066904017679477
    },
    {
      "totalUsdtValue": 14344442.54469286,
      "tokenPriceInUsdt": 412.11481112500616,
      "poolWeight": 0.0012,
      "symbol": "HBCH",
      "apy": 10.721096612951014
    },
    {
      "totalUsdtValue": 10627584.79178006,
      "tokenPriceInUsdt": 16.51396515422402,
      "poolWeight": 0.0012,
      "symbol": "HDOT",
      "apy": 14.470658893215797
    },
    {
      "totalUsdtValue": 13106813.045511186,
      "tokenPriceInUsdt": 133.15256482807374,
      "poolWeight": 0.0012,
      "symbol": "HLTC",
      "apy": 11.73345143831485
    }
  ],
  "lps": [
    {
      "totalUsdtValue": 176869824.70921645,
      "tokenPriceInUsdt": 34304.78058570763,
      "poolWeight": 0.1469,
      "symbol": "HBTC/USDT",
      "apy": 106.44118216909145
    },
    {
      "totalUsdtValue": 168700675.9364989,
      "tokenPriceInUsdt": 1377.9681866410256,
      "poolWeight": 0.1479,
      "symbol": "ETH/USDT",
      "apy": 112.3551516446846
    },
    {
      "totalUsdtValue": 111421898.95345539,
      "tokenPriceInUsdt": 0.9988811239412843,
      "poolWeight": 0.03,
      "symbol": "HUSD/USDT",
      "apy": 34.505818834774
    },
    {
      "totalUsdtValue": 40792344.80022501,
      "tokenPriceInUsdt": 133.15372588266828,
      "poolWeight": 0.045,
      "symbol": "HLTC/USDT",
      "apy": 141.37593260488003
    },
    {
      "totalUsdtValue": 40384135.80858749,
      "tokenPriceInUsdt": 412.12855974704667,
      "poolWeight": 0.045,
      "symbol": "HBCH/USDT",
      "apy": 142.8049820505334
    },
    {
      "totalUsdtValue": 39356319.31428337,
      "tokenPriceInUsdt": 16.51393081625325,
      "poolWeight": 0.045,
      "symbol": "HDOT/USDT",
      "apy": 146.53442927978872
    },
    {
      "totalUsdtValue": 37527950.347039066,
      "tokenPriceInUsdt": 22.335434326676772,
      "poolWeight": 0.045,
      "symbol": "HFIL/USDT",
      "apy": 153.67361489079187
    },
    {
      "totalUsdtValue": 52287309.630300075,
      "tokenPriceInUsdt": 3.048532881977921,
      "poolWeight": 0.22,
      "symbol": "MDX/USDT",
      "apy": 539.2225220445074
    },
    {
      "totalUsdtValue": 85947554.62045538,
      "tokenPriceInUsdt": 6.380341567993995,
      "poolWeight": 0.1,
      "symbol": "WHT/HUSD",
      "apy": 149.11046147047267
    },
    {
      "totalUsdtValue": 86665685.88021943,
      "tokenPriceInUsdt": 6.380357859894746,
      "poolWeight": 0.09,
      "symbol": "WHT/USDT",
      "apy": 133.08740894850317
    },
    {
      "totalUsdtValue": 4844685.439213666,
      "tokenPriceInUsdt": 0.004291108119113331,
      "poolWeight": 0.0056,
      "symbol": "HPT/USDT",
      "apy": 148.13718305981732
    },
    {
      "totalUsdtValue": 16611822.251322765,
      "tokenPriceInUsdt": 3.048731784363106,
      "poolWeight": 0.0595,
      "symbol": "MDX/WHT",
      "apy": 459.0302741027156
    }
  ],
  "time": "2021-01-31 07:54"
}