{
  "minging": [
    {
      "id": 1,
      "pool_id": 0,
      "token0": "0x0298c2b32eaE4da002a15f36fdf7615BEa3DA047",
      "token1": "0x5545153CCFcA01fbd7Dd11C0b23ba694D9509A6F",
      "alloc_mdx_amt": "12646459150029499426006",
      "total_quantity": "3193991341851916722997666260",
      "pool_quantity": "10579992247410559358928111",
      "alloc_point": "150",
      "apy": "1373.9933321898172",
      "symbol0": "HUSD",
      "symbol1": "HT"
    },
    {
      "id": 2,
      "pool_id": 1,
      "token0": "0x64FF637fB478863B7468bc97D30a5bF3A428a1fD",
      "token1": "0xa71EdC38d189767582C38A3145b5873052c3e47a",
      "alloc_mdx_amt": "10954903236809361470153",
      "total_quantity": "3223395485929830457563974557",
      "pool_quantity": "9217186383844503921984195",
      "alloc_point": "150",
      "apy": "1586.2518906713851",
      "symbol0": "ETH",
      "symbol1": "USDT"
    },
    {
      "id": 3,
      "pool_id": 2,
      "token0": "0x66a79D23E58475D2738179Ca52cd0b41d73f0BEa",
      "token1": "0xa71EdC38d189767582C38A3145b5873052c3e47a",
      "alloc_mdx_amt": "49293285442557622270877",
      "total_quantity": "3240705375861502707511155293",
      "pool_quantity": "56465175657531003164247953",
      "alloc_point": "150",
      "apy": "257.51086512666393",
      "symbol0": "HBTC",
      "symbol1": "USDT"
    },
    {
      "id": 4,
      "pool_id": 3,
      "token0": "0x0298c2b32eaE4da002a15f36fdf7615BEa3DA047",
      "token1": "0xa71EdC38d189767582C38A3145b5873052c3e47a",
      "alloc_mdx_amt": "25891954352267694456328",
      "total_quantity": "8575650254012571149364797695",
      "pool_quantity": "21728711469305824270931752",
      "alloc_point": "400",
      "apy": "1784.2469194493694",
      "symbol0": "HUSD",
      "symbol1": "USDT"
    },
    {
      "id": 5,
      "pool_id": 4,
      "token0": "0x25D2e80cB6B86881Fd7e07dd263Fb79f4AbE033c",
      "token1": "0xa71EdC38d189767582C38A3145b5873052c3e47a",
      "alloc_mdx_amt": "53663378067901785374575",
      "total_quantity": "560189256943381420511268887",
      "pool_quantity": "47353215563558263894750264",
      "alloc_point": "20",
      "apy": "40.931132633352895",
      "symbol0": "MDX",
      "symbol1": "USDT"
    },
    {
      "id": 6,
      "pool_id": 5,
      "token0": "0x0298c2b32eaE4da002a15f36fdf7615BEa3DA047",
      "token1": "0xa042fb0e60125A4022670014AC121931e7501Af4",
      "alloc_mdx_amt": "12247450640898992290073",
      "total_quantity": "253521164154285449153241048",
      "pool_quantity": "11455267738378504324380022",
      "alloc_point": "10",
      "apy": "84.60281160335792",
      "symbol0": "HUSD",
      "symbol1": "BAG"
    },
    {
      "id": 7,
      "pool_id": 6,
      "token0": "0x66a79D23E58475D2738179Ca52cd0b41d73f0BEa",
      "token1": "0xa042fb0e60125A4022670014AC121931e7501Af4",
      "alloc_mdx_amt": "2146368321665120372175",
      "total_quantity": "217944751441963028463068397",
      "pool_quantity": "1578062838733427680244174",
      "alloc_point": "10",
      "apy": "614.132432540631",
      "symbol0": "HBTC",
      "symbol1": "BAG"
    },
    {
      "id": 8,
      "pool_id": 7,
      "token0": "0xA2c49cEe16a5E5bDEFDe931107dc1fae9f7773E3",
      "token1": "0xa71EdC38d189767582C38A3145b5873052c3e47a",
      "alloc_mdx_amt": "4367502032470374048298",
      "total_quantity": "657916031417783678865975340",
      "pool_quantity": "3894710423511822797114602",
      "alloc_point": "30",
      "apy": "747.9691581206206",
      "symbol0": "HDOT",
      "symbol1": "USDT"
    },
    {
      "id": 9,
      "pool_id": 8,
      "token0": "0xa71EdC38d189767582C38A3145b5873052c3e47a",
      "token1": "0xecb56cf772B5c9A6907FB7d32387Da2fCbfB63b4",
      "alloc_mdx_amt": "2093874730800121516300",
      "total_quantity": "644937102543903382747859456",
      "pool_quantity": "1826901459950555538058894",
      "alloc_point": "30",
      "apy": "1571.0875601821597",
      "symbol0": "USDT",
      "symbol1": "HLTC"
    },
    {
      "id": 10,
      "pool_id": 9,
      "token0": "0xa71EdC38d189767582C38A3145b5873052c3e47a",
      "token1": "0xeF3CEBD77E0C52cb6f60875d9306397B5Caca375",
      "alloc_mdx_amt": "1089729846453953661144",
      "total_quantity": "643791546183844590798741000",
      "pool_quantity": "921997317986763504101845",
      "alloc_point": "30",
      "apy": "3168.4555554225194",
      "symbol0": "USDT",
      "symbol1": "HBCH"
    },
    {
      "id": 11,
      "pool_id": 10,
      "token0": "0xa71EdC38d189767582C38A3145b5873052c3e47a",
      "token1": "0xE499Ef4616993730CEd0f31FA2703B92B50bB536",
      "alloc_mdx_amt": "1524756728740522378209",
      "total_quantity": "102610178402604704339248082",
      "pool_quantity": "1285389446984335710943717",
      "alloc_point": "5",
      "apy": "376.9750482389312",
      "symbol0": "USDT",
      "symbol1": "HPT"
    },
    {
      "id": 12,
      "pool_id": 11,
      "token0": "0x5545153CCFcA01fbd7Dd11C0b23ba694D9509A6F",
      "token1": "0xa71EdC38d189767582C38A3145b5873052c3e47a",
      "alloc_mdx_amt": "17386221512938620685893",
      "total_quantity": "368814535340110480201946723",
      "pool_quantity": "23066649425761276338399317",
      "alloc_point": "15",
      "apy": "63.022844661698464",
      "symbol0": "HT",
      "symbol1": "USDT"
    }
  ],
  "single": [
    {
      "totalUsdtValue": 50826627.230850436,
      "tokenPriceInUsdt": 9.038554863225437,
      "poolWeight": 0,
      "symbol": "WHT",
      "apy": 0
    },
    {
      "totalUsdtValue": 1357831.186756554,
      "tokenPriceInUsdt": 42753.02029113825,
      "poolWeight": 0,
      "symbol": "HBTC",
      "apy": 0
    },
    {
      "totalUsdtValue": 765105.0764333165,
      "tokenPriceInUsdt": 0.9988487626002095,
      "poolWeight": 0,
      "symbol": "HUSD",
      "apy": 0
    },
    {
      "totalUsdtValue": 362487.52856269816,
      "tokenPriceInUsdt": 1695.7151697641427,
      "poolWeight": 0,
      "symbol": "ETH",
      "apy": 0
    },
    {
      "totalUsdtValue": 182905.71691399833,
      "tokenPriceInWeth": 1,
      "poolWeight": 0,
      "symbol": "USDT",
      "apy": 0
    },
    {
      "totalUsdtValue": 6850730.918953488,
      "tokenPriceInUsdt": 470.8651281062175,
      "poolWeight": 0,
      "symbol": "HBCH",
      "apy": 0
    },
    {
      "totalUsdtValue": 8825.24356806402,
      "tokenPriceInUsdt": 22.65238851101725,
      "poolWeight": 0,
      "symbol": "HDOT",
      "apy": 0
    },
    {
      "totalUsdtValue": 45404.07260111847,
      "tokenPriceInUsdt": 161.3956690771383,
      "poolWeight": 0,
      "symbol": "HLTC",
      "apy": 0
    }
  ],
  "lps": [
    {
      "totalUsdtValue": 225281998.0525886,
      "tokenPriceInUsdt": 42754.60476942022,
      "poolWeight": 0.1469,
      "symbol": "HBTC/USDT",
      "apy": 69.199521953626
    },
    {
      "totalUsdtValue": 180294339.08054575,
      "tokenPriceInUsdt": 1695.7497205273608,
      "poolWeight": 0.1479,
      "symbol": "ETH/USDT",
      "apy": 87.05503027493351
    },
    {
      "totalUsdtValue": 81105918.04331137,
      "tokenPriceInUsdt": 0.9988414335435324,
      "poolWeight": 0.03,
      "symbol": "HUSD/USDT",
      "apy": 39.25332933258899
    },
    {
      "totalUsdtValue": 45037120.22854265,
      "tokenPriceInUsdt": 161.3991976393628,
      "poolWeight": 0.045,
      "symbol": "HLTC/USDT",
      "apy": 106.03510933715488
    },
    {
      "totalUsdtValue": 43669200.30817287,
      "tokenPriceInUsdt": 470.8706271319892,
      "poolWeight": 0.045,
      "symbol": "HBCH/USDT",
      "apy": 109.35661596647905
    },
    {
      "totalUsdtValue": 35049564.78705125,
      "tokenPriceInUsdt": 22.653966716804895,
      "poolWeight": 0.045,
      "symbol": "HDOT/USDT",
      "apy": 136.2503642107528
    },
    {
      "totalUsdtValue": 39719185.644575156,
      "tokenPriceInUsdt": 22.79623868755487,
      "poolWeight": 0.0445,
      "symbol": "HFIL/USDT",
      "apy": 118.89605998957586
    },
    {
      "totalUsdtValue": 59670716.73464549,
      "tokenPriceInUsdt": 2.5238973794516424,
      "poolWeight": 0.22,
      "symbol": "MDX/USDT",
      "apy": 391.2633906652746
    },
    {
      "totalUsdtValue": 87400710.30406363,
      "tokenPriceInUsdt": 9.038902426608525,
      "poolWeight": 0.098,
      "symbol": "WHT/HUSD",
      "apy": 118.99231156841408
    },
    {
      "totalUsdtValue": 87788696.37140213,
      "tokenPriceInUsdt": 9.038939225581387,
      "poolWeight": 0.09,
      "symbol": "WHT/USDT",
      "apy": 108.79569158791544
    },
    {
      "totalUsdtValue": 2443962.2375786365,
      "tokenPriceInUsdt": 0.008303889410442147,
      "poolWeight": 0.0056,
      "symbol": "HPT/USDT",
      "apy": 243.1651448593268
    },
    {
      "totalUsdtValue": 21625020.045126077,
      "tokenPriceInUsdt": 2.523916654157592,
      "poolWeight": 0.0796,
      "symbol": "MDX/WHT",
      "apy": 390.6288695356104
    }
  ],
  "time": "2021-02-09 03:06"
}